{
   "CodeGenerationMode": 4,
   "ContextClassName": "EscapeRoomUnityContext",
   "ContextNamespace": null,
   "FilterSchemas": false,
   "IncludeConnectionString": false,
   "ModelNamespace": null,
   "OutputContextPath": null,
   "OutputPath": "Entities",
   "PreserveCasingWithRegex": true,
   "ProjectRootNamespace": "EscapeRoomAPI",
   "Schemas": null,
   "SelectedHandlebarsLanguage": 2,
   "SelectedToBeGenerated": 0,
   "T4TemplatePath": null,
   "Tables": [
      {
         "Name": "[dbo].[GameSession]",
         "ObjectType": 0
      },
      {
         "Name": "[dbo].[Leaderboard]",
         "ObjectType": 0
      },
      {
         "Name": "[dbo].[Player]",
         "ObjectType": 0
      },
      {
         "Name": "[dbo].[PlayerGameAnswer]",
         "ObjectType": 0
      },
      {
         "Name": "[dbo].[PlayerGameSession]",
         "ObjectType": 0
      },
      {
         "Name": "[dbo].[Question]",
         "ObjectType": 0
      },
      {
         "Name": "[dbo].[QuestionAnswer]",
         "ObjectType": 0
      }
   ],
   "UiHint": null,
   "UncountableWords": null,
   "UseAsyncStoredProcedureCalls": true,
   "UseBoolPropertiesWithoutDefaultSql": false,
   "UseDatabaseNames": false,
   "UseDateOnlyTimeOnly": true,
   "UseDbContextSplitting": false,
   "UseDecimalDataAnnotationForSprocResult": true,
   "UseFluentApiOnly": true,
   "UseHandleBars": false,
   "UseHierarchyId": false,
   "UseInflector": true,
   "UseLegacyPluralizer": false,
   "UseManyToManyEntity": false,
   "UseNoDefaultConstructor": false,
   "UseNoNavigations": false,
   "UseNoObjectFilter": false,
   "UseNodaTime": false,
   "UseNullableReferences": false,
   "UsePrefixNavigationNaming": false,
   "UseSchemaFolders": false,
   "UseSchemaNamespaces": false,
   "UseSpatial": false,
   "UseT4": false
}